setup.py
gbpdf_probability/Binomialdistribution.py
gbpdf_probability/Gaussiandistribution.py
gbpdf_probability/Generaldistribution.py
gbpdf_probability/__init__.py
gbpdf_probability.egg-info/PKG-INFO
gbpdf_probability.egg-info/SOURCES.txt
gbpdf_probability.egg-info/dependency_links.txt
gbpdf_probability.egg-info/not-zip-safe
gbpdf_probability.egg-info/top_level.txt